jwt_manager/__init__.py
jwt_manager/exceptions.py
jwt_manager/jwt_manager.py
jwt_manager-0.1.0.dist-info/licenses/LICENSE.txt
jwt_manager-0.1.0.dist-info/METADATA
jwt_manager-0.1.0.dist-info/WHEEL
jwt_manager-0.1.0.dist-info/top_level.txt
jwt_manager-0.1.0.dist-info/RECORD
