Metadata-Version: 2.4
Name: jwt_manager
Version: 0.1.0
Summary: A lightweight utility to create, validate, and refresh JWT tokens easily.
Home-page: https://github.com/your_github_username/jwt_manager
Author: Faizan Utilities
Author-email: support@example.com
Project-URL: Bug Tracker, https://github.com/your_github_username/jwt_manager/issues
Classifier: Programming Language :: Python :: 3
Classifier: License :: OSI Approved :: MIT License
Classifier: Operating System :: OS Independent
Requires-Python: >=3.7
License-File: LICENSE.txt
Requires-Dist: PyJWT
Dynamic: author
Dynamic: author-email
Dynamic: classifier
Dynamic: description
Dynamic: description-content-type
Dynamic: home-page
Dynamic: license-file
Dynamic: project-url
Dynamic: requires-dist
Dynamic: requires-python
Dynamic: summary
